{
  "db_name": "PostgreSQL",
  "query": "SELECT id, prefix, welcome_msg, voice_multiplier, text_multiplier FROM guilds",
  "describe": {
    "columns": [
      {
        "ordinal": 0,
        "name": "id",
        "type_info": "Int8"
      },
      {
        "ordinal": 1,
        "name": "prefix",
        "type_info": "Varchar"
      },
      {
        "ordinal": 2,
        "name": "welcome_msg",
        "type_info": "Varchar"
      },
      {
        "ordinal": 3,
        "name": "voice_multiplier",
        "type_info": "Int8"
      },
      {
        "ordinal": 4,
        "name": "text_multiplier",
        "type_info": "Int8"
      }
    ],
    "parameters": {
      "Left": []
    },
    "nullable": [
      false,
      false,
      true,
      false,
      false
    ]
  },
  "hash": "4ffe892431deafc694b27edc10b0acf8d9ecf47006cf5343764756a4e6099253"
}
